remembrance/__init__.py
remembrance/access_async.py
remembrance/ipstat_async.py
remembrance/models.py
remembrance/remembrance_tkinter_frame.py
remembrance-20.0.0.dist-info/METADATA
remembrance-20.0.0.dist-info/WHEEL
remembrance-20.0.0.dist-info/top_level.txt
remembrance-20.0.0.dist-info/RECORD
