Metadata-Version: 2.1
Name: remembrance
Version: 20.0.0
Summary: UNKNOWN
Home-page: UNKNOWN
Author: CyberRiscV
Author-email: cyberiscv@gmail.com
License: MIT
Platform: UNKNOWN
Classifier: License :: OSI Approved :: MIT License
Classifier: Programming Language :: Python
Classifier: Programming Language :: Python :: 3
Requires-Dist: rich
